Metadata-Version: 2.1
Name: m3gnet
Version: 0.0.8
Summary: Materials Graph with Three-body Interactions
Download-URL: https://github.com/materialsvirtuallab/m3gnet
Author: Chi Chen
Author-email: chen08013@gmail.com
License: BSD
Keywords: materials,science,machine,learning,deep,graph,networks,neural,force field,interatomic potential
Platform: UNKNOWN
Classifier: Programming Language :: Python :: 3
Classifier: Programming Language :: Python :: 3.8
Classifier: Programming Language :: Python :: 3.9
Classifier: Development Status :: 4 - Beta
Classifier: Intended Audience :: Science/Research
Classifier: License :: OSI Approved :: BSD License
Classifier: Operating System :: OS Independent
Classifier: Topic :: Scientific/Engineering :: Information Analysis
Classifier: Topic :: Scientific/Engineering :: Physics
Classifier: Topic :: Scientific/Engineering :: Chemistry
Classifier: Topic :: Software Development :: Libraries :: Python Modules
License-File: LICENSE
Requires-Dist: pymatgen
Requires-Dist: tensorflow
Requires-Dist: numpy
Requires-Dist: monty
Requires-Dist: sympy
Requires-Dist: cython
Requires-Dist: ase
Provides-Extra: model_saving
Requires-Dist: h5py ; extra == 'model_saving'
Provides-Extra: tensorflow_with_gpu
Requires-Dist: tensorflow-gpu (>=2.7) ; extra == 'tensorflow_with_gpu'
